<?xml version="1.0"?>
<opencv_storage>
<globfeat type_id="opencv-matrix">
  <rows>1</rows>
  <cols>64</cols>
  <dt>f</dt>
  <data>
    6.85408974e+00 1.31026182e+01 0. 0. 8.88512993e+00 2.27755127e+01
    1.72022114e+01 8.44033718e+00 0. 0. 0. 0. 0. 0. 0. 0. 0. 0. 0. 0. 0.
    0. 0. 0. 0. 0. 0. 0. 0. 0. 0. 0. 2.50209103e+01 3.85308075e+00 0. 0.
    4.46989517e+01 3.16177711e+01 1.54980669e+01 1.01444817e+01
    2.78772278e+01 0. 0. 0. 6.95590973e+00 0. 0. 0. 4.76946020e+00
    7.30424070e+00 0. 0. 0. 0. 0. 0. 0. 0. 0. 0. 0. 0. 0. 0.</data></globfeat>
</opencv_storage>
