<?xml version="1.0"?>
<opencv_storage>
<my_random_trees type_id="opencv-ml-random-trees">
  <nclasses>0</nclasses>
  <nsamples>50400</nsamples>
  <nactive_vars>15</nactive_vars>
  <oob_error>1.7086265405214240e-03</oob_error>
  <ntrees>1</ntrees>
  <is_classifier>0</is_classifier>
  <var_all>225</var_all>
  <var_count>225</var_count>
  <ord_var_count>225</ord_var_count>
  <cat_var_count>0</cat_var_count>
  <training_params>
    <use_surrogates>0</use_surrogates>
    <regression_accuracy>0.</regression_accuracy>
    <max_depth>10</max_depth>
    <min_sample_count>10</min_sample_count>
    <cross_validation_folds>0</cross_validation_folds></training_params>
  <var_type>
    0 0 0 0 0 0 0 0 0 0 0 0 0 0 0 0 0 0 0 0 0 0 0 0 0 0 0 0 0 0 0 0 0 0
    0 0 0 0 0 0 0 0 0 0 0 0 0 0 0 0 0 0 0 0 0 0 0 0 0 0 0 0 0 0 0 0 0 0
    0 0 0 0 0 0 0 0 0 0 0 0 0 0 0 0 0 0 0 0 0 0 0 0 0 0 0 0 0 0 0 0 0 0
    0 0 0 0 0 0 0 0 0 0 0 0 0 0 0 0 0 0 0 0 0 0 0 0 0 0 0 0 0 0 0 0 0 0
    0 0 0 0 0 0 0 0 0 0 0 0 0 0 0 0 0 0 0 0 0 0 0 0 0 0 0 0 0 0 0 0 0 0
    0 0 0 0 0 0 0 0 0 0 0 0 0 0 0 0 0 0 0 0 0 0 0 0 0 0 0 0 0 0 0 0 0 0
    0 0 0 0 0 0 0 0 0 0 0 0 0 0 0 0 0 0 0 0 0</var_type>
  <trees>
    <_>
      <best_tree_idx>-1</best_tree_idx>
      <nodes>
        <_>
          <depth>0</depth>
          <sample_count>50400</sample_count>
          <value>6.8611111111111109e-02</value>
          <Tn>0</Tn>
          <complexity>0</complexity>
          <alpha>0.</alpha>
          <node_risk>3.2042427777777780e+03</node_risk>
          <tree_risk>0.</tree_risk>
          <tree_error>0.</tree_error>
          <splits>
            <_><var>175</var>
              <quality>3.2077824707031250e+03</quality>
              <le>4.6862745285034180e-01</le></_></splits></_>
        <_>
          <depth>1</depth>
          <sample_count>3417</sample_count>
          <value>9.6883230904302020e-01</value>
          <Tn>0</Tn>
          <complexity>0</complexity>
          <alpha>0.</alpha>
          <node_risk>9.7430640913081788e+01</node_risk>
          <tree_risk>0.</tree_risk>
          <tree_error>0.</tree_error>
          <splits>
            <_><var>151</var>
              <quality>3.2590603027343750e+03</quality>
              <le>4.6862745285034180e-01</le></_></splits></_>
        <_>
          <depth>2</depth>
          <sample_count>3290</sample_count>
          <value>9.9300911854103346e-01</value>
          <Tn>0</Tn>
          <complexity>0</complexity>
          <alpha>0.</alpha>
          <node_risk>2.1339209726443642e+01</node_risk>
          <tree_risk>0.</tree_risk>
          <tree_error>0.</tree_error>
          <splits>
            <_><var>171</var>
              <quality>3.2458876953125000e+03</quality>
              <le>5.2941177040338516e-02</le></_></splits></_>
        <_>
          <depth>3</depth>
          <sample_count>9</sample_count>
          <value>5.5555555555555558e-01</value>
          <Tn>0</Tn>
          <complexity>0</complexity>
          <alpha>0.</alpha>
          <node_risk>1.2222222222222223e+00</node_risk>
          <tree_risk>0.</tree_risk>
          <tree_error>0.</tree_error></_>
        <_>
          <depth>3</depth>
          <sample_count>3281</sample_count>
          <value>9.9420908259676932e-01</value>
          <Tn>0</Tn>
          <complexity>0</complexity>
          <alpha>0.</alpha>
          <node_risk>1.8389972569338624e+01</node_risk>
          <tree_risk>0.</tree_risk>
          <tree_error>0.</tree_error>
          <splits>
            <_><var>87</var>
              <quality>3.2488164062500000e+03</quality>
              <le>4.9803924560546875e-01</le></_></splits></_>
        <_>
          <depth>4</depth>
          <sample_count>3267</sample_count>
          <value>9.9693908784817875e-01</value>
          <Tn>0</Tn>
          <complexity>0</complexity>
          <alpha>0.</alpha>
          <node_risk>9.4693908784815903e+00</node_risk>
          <tree_risk>0.</tree_risk>
          <tree_error>0.</tree_error>
          <splits>
            <_><var>200</var>
              <quality>3.2482197265625000e+03</quality>
              <le>5.0392162799835205e-01</le></_></splits></_>
        <_>
          <depth>5</depth>
          <sample_count>74</sample_count>
          <value>8.7162162162162160e-01</value>
          <Tn>0</Tn>
          <complexity>0</complexity>
          <alpha>0.</alpha>
          <node_risk>8.0304054054054035e+00</node_risk>
          <tree_risk>0.</tree_risk>
          <tree_error>0.</tree_error>
          <splits>
            <_><var>148</var>
              <quality>5.8595069885253906e+01</quality>
              <le>2.3333334922790527e-01</le></_></splits></_>
        <_>
          <depth>6</depth>
          <sample_count>3</sample_count>
          <value>0.</value>
          <Tn>0</Tn>
          <complexity>0</complexity>
          <alpha>0.</alpha>
          <node_risk>0.</node_risk>
          <tree_risk>0.</tree_risk>
          <tree_error>0.</tree_error></_>
        <_>
          <depth>6</depth>
          <sample_count>71</sample_count>
          <value>9.0845070422535212e-01</value>
          <Tn>0</Tn>
          <complexity>0</complexity>
          <alpha>0.</alpha>
          <node_risk>5.6549295774647845e+00</node_risk>
          <tree_risk>0.</tree_risk>
          <tree_error>0.</tree_error>
          <splits>
            <_><var>114</var>
              <quality>6.0640625000000000e+01</quality>
              <le>4.6274510025978088e-01</le></_></splits></_>
        <_>
          <depth>7</depth>
          <sample_count>55</sample_count>
          <value>1.</value>
          <Tn>0</Tn>
          <complexity>0</complexity>
          <alpha>0.</alpha>
          <node_risk>0.</node_risk>
          <tree_risk>0.</tree_risk>
          <tree_error>0.</tree_error>
          <splits>
            <_><var>24</var>
              <quality>55.</quality>
              <le>1.0980392247438431e-01</le></_></splits></_>
        <_>
          <depth>8</depth>
          <sample_count>2</sample_count>
          <value>1.</value>
          <Tn>0</Tn>
          <complexity>0</complexity>
          <alpha>0.</alpha>
          <node_risk>0.</node_risk>
          <tree_risk>0.</tree_risk>
          <tree_error>0.</tree_error></_>
        <_>
          <depth>8</depth>
          <sample_count>53</sample_count>
          <value>1.</value>
          <Tn>0</Tn>
          <complexity>0</complexity>
          <alpha>0.</alpha>
          <node_risk>0.</node_risk>
          <tree_risk>0.</tree_risk>
          <tree_error>0.</tree_error>
          <splits>
            <_><var>4</var>
              <quality>53.</quality>
              <le>1.8235294520854950e-01</le></_></splits></_>
        <_>
          <depth>9</depth>
          <sample_count>1</sample_count>
          <value>1.</value>
          <Tn>0</Tn>
          <complexity>0</complexity>
          <alpha>0.</alpha>
          <node_risk>0.</node_risk>
          <tree_risk>0.</tree_risk>
          <tree_error>0.</tree_error></_>
        <_>
          <depth>9</depth>
          <sample_count>52</sample_count>
          <value>1.</value>
          <Tn>0</Tn>
          <complexity>0</complexity>
          <alpha>0.</alpha>
          <node_risk>0.</node_risk>
          <tree_risk>0.</tree_risk>
          <tree_error>0.</tree_error>
          <splits>
            <_><var>47</var>
              <quality>52.</quality>
              <le>1.2941177189350128e-01</le></_></splits></_>
        <_>
          <depth>10</depth>
          <sample_count>4</sample_count>
          <value>1.</value>
          <Tn>0</Tn>
          <complexity>0</complexity>
          <alpha>0.</alpha>
          <node_risk>0.</node_risk>
          <tree_risk>0.</tree_risk>
          <tree_error>0.</tree_error></_>
        <_>
          <depth>10</depth>
          <sample_count>48</sample_count>
          <value>1.</value>
          <Tn>0</Tn>
          <complexity>0</complexity>
          <alpha>0.</alpha>
          <node_risk>0.</node_risk>
          <tree_risk>0.</tree_risk>
          <tree_error>0.</tree_error></_>
        <_>
          <depth>7</depth>
          <sample_count>16</sample_count>
          <value>5.9375000000000000e-01</value>
          <Tn>0</Tn>
          <complexity>0</complexity>
          <alpha>0.</alpha>
          <node_risk>3.6093750000000000e+00</node_risk>
          <tree_risk>0.</tree_risk>
          <tree_error>0.</tree_error>
          <splits>
            <_><var>31</var>
              <quality>8.2045450210571289e+00</quality>
              <le>2.0588235557079315e-01</le></_></splits></_>
        <_>
          <depth>8</depth>
          <sample_count>5</sample_count>
          <value>0.</value>
          <Tn>0</Tn>
          <complexity>0</complexity>
          <alpha>0.</alpha>
          <node_risk>0.</node_risk>
          <tree_risk>0.</tree_risk>
          <tree_error>0.</tree_error></_>
        <_>
          <depth>8</depth>
          <sample_count>11</sample_count>
          <value>8.6363636363636365e-01</value>
          <Tn>0</Tn>
          <complexity>0</complexity>
          <alpha>0.</alpha>
          <node_risk>1.0454545454545450e+00</node_risk>
          <tree_risk>0.</tree_risk>
          <tree_error>0.</tree_error>
          <splits>
            <_><var>126</var>
              <quality>9.1250000000000000e+00</quality>
              <le>4.4509804248809814e-01</le></_></splits></_>
        <_>
          <depth>9</depth>
          <sample_count>9</sample_count>
          <value>1.</value>
          <Tn>0</Tn>
          <complexity>0</complexity>
          <alpha>0.</alpha>
          <node_risk>0.</node_risk>
          <tree_risk>0.</tree_risk>
          <tree_error>0.</tree_error></_>
        <_>
          <depth>9</depth>
          <sample_count>2</sample_count>
          <value>2.5000000000000000e-01</value>
          <Tn>0</Tn>
          <complexity>0</complexity>
          <alpha>0.</alpha>
          <node_risk>1.2500000000000000e-01</node_risk>
          <tree_risk>0.</tree_risk>
          <tree_error>0.</tree_error></_>
        <_>
          <depth>5</depth>
          <sample_count>3193</sample_count>
          <value>9.9984340745380518e-01</value>
          <Tn>0</Tn>
          <complexity>0</complexity>
          <alpha>0.</alpha>
          <node_risk>2.4992170372706823e-01</node_risk>
          <tree_risk>0.</tree_risk>
          <tree_error>0.</tree_error>
          <splits>
            <_><var>96</var>
              <quality>3.1920500488281250e+03</quality>
              <le>3.0980393290519714e-01</le></_></splits></_>
        <_>
          <depth>6</depth>
          <sample_count>5</sample_count>
          <value>9.0000000000000002e-01</value>
          <Tn>0</Tn>
          <complexity>0</complexity>
          <alpha>0.</alpha>
          <node_risk>2.0000000000000018e-01</node_risk>
          <tree_risk>0.</tree_risk>
          <tree_error>0.</tree_error></_>
        <_>
          <depth>6</depth>
          <sample_count>3188</sample_count>
          <value>1.</value>
          <Tn>0</Tn>
          <complexity>0</complexity>
          <alpha>0.</alpha>
          <node_risk>0.</node_risk>
          <tree_risk>0.</tree_risk>
          <tree_error>0.</tree_error>
          <splits>
            <_><var>14</var>
              <quality>3188.</quality>
              <le>1.9607844296842813e-03</le></_></splits></_>
        <_>
          <depth>7</depth>
          <sample_count>2</sample_count>
          <value>1.</value>
          <Tn>0</Tn>
          <complexity>0</complexity>
          <alpha>0.</alpha>
          <node_risk>0.</node_risk>
          <tree_risk>0.</tree_risk>
          <tree_error>0.</tree_error></_>
        <_>
          <depth>7</depth>
          <sample_count>3186</sample_count>
          <value>1.</value>
          <Tn>0</Tn>
          <complexity>0</complexity>
          <alpha>0.</alpha>
          <node_risk>0.</node_risk>
          <tree_risk>0.</tree_risk>
          <tree_error>0.</tree_error>
          <splits>
            <_><var>20</var>
              <quality>3186.</quality>
              <le>3.9215688593685627e-03</le></_></splits></_>
        <_>
          <depth>8</depth>
          <sample_count>5</sample_count>
          <value>1.</value>
          <Tn>0</Tn>
          <complexity>0</complexity>
          <alpha>0.</alpha>
          <node_risk>0.</node_risk>
          <tree_risk>0.</tree_risk>
          <tree_error>0.</tree_error></_>
        <_>
          <depth>8</depth>
          <sample_count>3181</sample_count>
          <value>1.</value>
          <Tn>0</Tn>
          <complexity>0</complexity>
          <alpha>0.</alpha>
          <node_risk>0.</node_risk>
          <tree_risk>0.</tree_risk>
          <tree_error>0.</tree_error>
          <splits>
            <_><var>4</var>
              <quality>3181.</quality>
              <le>1.1568627506494522e-01</le></_></splits></_>
        <_>
          <depth>9</depth>
          <sample_count>2</sample_count>
          <value>1.</value>
          <Tn>0</Tn>
          <complexity>0</complexity>
          <alpha>0.</alpha>
          <node_risk>0.</node_risk>
          <tree_risk>0.</tree_risk>
          <tree_error>0.</tree_error></_>
        <_>
          <depth>9</depth>
          <sample_count>3179</sample_count>
          <value>1.</value>
          <Tn>0</Tn>
          <complexity>0</complexity>
          <alpha>0.</alpha>
          <node_risk>0.</node_risk>
          <tree_risk>0.</tree_risk>
          <tree_error>0.</tree_error>
          <splits>
            <_><var>10</var>
              <quality>3179.</quality>
              <le>9.2156864702701569e-02</le></_></splits></_>
        <_>
          <depth>10</depth>
          <sample_count>1</sample_count>
          <value>1.</value>
          <Tn>0</Tn>
          <complexity>0</complexity>
          <alpha>0.</alpha>
          <node_risk>0.</node_risk>
          <tree_risk>0.</tree_risk>
          <tree_error>0.</tree_error></_>
        <_>
          <depth>10</depth>
          <sample_count>3178</sample_count>
          <value>1.</value>
          <Tn>0</Tn>
          <complexity>0</complexity>
          <alpha>0.</alpha>
          <node_risk>0.</node_risk>
          <tree_risk>0.</tree_risk>
          <tree_error>0.</tree_error></_>
        <_>
          <depth>4</depth>
          <sample_count>14</sample_count>
          <value>3.5714285714285715e-01</value>
          <Tn>0</Tn>
          <complexity>0</complexity>
          <alpha>0.</alpha>
          <node_risk>3.2142857142857144e+00</node_risk>
          <tree_risk>0.</tree_risk>
          <tree_error>0.</tree_error>
          <splits>
            <_><var>56</var>
              <quality>4.1666665077209473e+00</quality>
              <le>1.9411765038967133e-01</le></_></splits></_>
        <_>
          <depth>5</depth>
          <sample_count>6</sample_count>
          <value>8.3333333333333337e-01</value>
          <Tn>0</Tn>
          <complexity>0</complexity>
          <alpha>0.</alpha>
          <node_risk>8.3333333333333304e-01</node_risk>
          <tree_risk>0.</tree_risk>
          <tree_error>0.</tree_error></_>
        <_>
          <depth>5</depth>
          <sample_count>8</sample_count>
          <value>0.</value>
          <Tn>0</Tn>
          <complexity>0</complexity>
          <alpha>0.</alpha>
          <node_risk>0.</node_risk>
          <tree_risk>0.</tree_risk>
          <tree_error>0.</tree_error></_>
        <_>
          <depth>2</depth>
          <sample_count>127</sample_count>
          <value>3.4251968503937008e-01</value>
          <Tn>0</Tn>
          <complexity>0</complexity>
          <alpha>0.</alpha>
          <node_risk>2.4350393700787400e+01</node_risk>
          <tree_risk>0.</tree_risk>
          <tree_error>0.</tree_error>
          <splits>
            <_><var>20</var>
              <quality>2.5135833740234375e+01</quality>
              <le>1.2745098769664764e-01</le></_></splits></_>
        <_>
          <depth>3</depth>
          <sample_count>27</sample_count>
          <value>8.8888888888888884e-01</value>
          <Tn>0</Tn>
          <complexity>0</complexity>
          <alpha>0.</alpha>
          <node_risk>2.1666666666666679e+00</node_risk>
          <tree_risk>0.</tree_risk>
          <tree_error>0.</tree_error>
          <splits>
            <_><var>76</var>
              <quality>2.3250000000000000e+01</quality>
              <le>3.0980393290519714e-01</le></_></splits></_>
        <_>
          <depth>4</depth>
          <sample_count>4</sample_count>
          <value>2.5000000000000000e-01</value>
          <Tn>0</Tn>
          <complexity>0</complexity>
          <alpha>0.</alpha>
          <node_risk>2.5000000000000000e-01</node_risk>
          <tree_risk>0.</tree_risk>
          <tree_error>0.</tree_error></_>
        <_>
          <depth>4</depth>
          <sample_count>23</sample_count>
          <value>1.</value>
          <Tn>0</Tn>
          <complexity>0</complexity>
          <alpha>0.</alpha>
          <node_risk>0.</node_risk>
          <tree_risk>0.</tree_risk>
          <tree_error>0.</tree_error>
          <splits>
            <_><var>18</var>
              <quality>23.</quality>
              <le>2.5490196421742439e-02</le></_></splits></_>
        <_>
          <depth>5</depth>
          <sample_count>3</sample_count>
          <value>1.</value>
          <Tn>0</Tn>
          <complexity>0</complexity>
          <alpha>0.</alpha>
          <node_risk>0.</node_risk>
          <tree_risk>0.</tree_risk>
          <tree_error>0.</tree_error></_>
        <_>
          <depth>5</depth>
          <sample_count>20</sample_count>
          <value>1.</value>
          <Tn>0</Tn>
          <complexity>0</complexity>
          <alpha>0.</alpha>
          <node_risk>0.</node_risk>
          <tree_risk>0.</tree_risk>
          <tree_error>0.</tree_error>
          <splits>
            <_><var>23</var>
              <quality>20.</quality>
              <le>4.5098040252923965e-02</le></_></splits></_>
        <_>
          <depth>6</depth>
          <sample_count>3</sample_count>
          <value>1.</value>
          <Tn>0</Tn>
          <complexity>0</complexity>
          <alpha>0.</alpha>
          <node_risk>0.</node_risk>
          <tree_risk>0.</tree_risk>
          <tree_error>0.</tree_error></_>
        <_>
          <depth>6</depth>
          <sample_count>17</sample_count>
          <value>1.</value>
          <Tn>0</Tn>
          <complexity>0</complexity>
          <alpha>0.</alpha>
          <node_risk>0.</node_risk>
          <tree_risk>0.</tree_risk>
          <tree_error>0.</tree_error>
          <splits>
            <_><var>11</var>
              <quality>17.</quality>
              <le>9.0196080505847931e-02</le></_></splits></_>
        <_>
          <depth>7</depth>
          <sample_count>2</sample_count>
          <value>1.</value>
          <Tn>0</Tn>
          <complexity>0</complexity>
          <alpha>0.</alpha>
          <node_risk>0.</node_risk>
          <tree_risk>0.</tree_risk>
          <tree_error>0.</tree_error></_>
        <_>
          <depth>7</depth>
          <sample_count>15</sample_count>
          <value>1.</value>
          <Tn>0</Tn>
          <complexity>0</complexity>
          <alpha>0.</alpha>
          <node_risk>0.</node_risk>
          <tree_risk>0.</tree_risk>
          <tree_error>0.</tree_error>
          <splits>
            <_><var>5</var>
              <quality>15.</quality>
              <le>1.0000000149011612e-01</le></_></splits></_>
        <_>
          <depth>8</depth>
          <sample_count>1</sample_count>
          <value>1.</value>
          <Tn>0</Tn>
          <complexity>0</complexity>
          <alpha>0.</alpha>
          <node_risk>0.</node_risk>
          <tree_risk>0.</tree_risk>
          <tree_error>0.</tree_error></_>
        <_>
          <depth>8</depth>
          <sample_count>14</sample_count>
          <value>1.</value>
          <Tn>0</Tn>
          <complexity>0</complexity>
          <alpha>0.</alpha>
          <node_risk>0.</node_risk>
          <tree_risk>0.</tree_risk>
          <tree_error>0.</tree_error>
          <splits>
            <_><var>6</var>
              <quality>14.</quality>
              <le>3.7254903465509415e-02</le></_></splits></_>
        <_>
          <depth>9</depth>
          <sample_count>1</sample_count>
          <value>1.</value>
          <Tn>0</Tn>
          <complexity>0</complexity>
          <alpha>0.</alpha>
          <node_risk>0.</node_risk>
          <tree_risk>0.</tree_risk>
          <tree_error>0.</tree_error></_>
        <_>
          <depth>9</depth>
          <sample_count>13</sample_count>
          <value>1.</value>
          <Tn>0</Tn>
          <complexity>0</complexity>
          <alpha>0.</alpha>
          <node_risk>0.</node_risk>
          <tree_risk>0.</tree_risk>
          <tree_error>0.</tree_error>
          <splits>
            <_><var>14</var>
              <quality>13.</quality>
              <le>1.1176470667123795e-01</le></_></splits></_>
        <_>
          <depth>10</depth>
          <sample_count>1</sample_count>
          <value>1.</value>
          <Tn>0</Tn>
          <complexity>0</complexity>
          <alpha>0.</alpha>
          <node_risk>0.</node_risk>
          <tree_risk>0.</tree_risk>
          <tree_error>0.</tree_error></_>
        <_>
          <depth>10</depth>
          <sample_count>12</sample_count>
          <value>1.</value>
          <Tn>0</Tn>
          <complexity>0</complexity>
          <alpha>0.</alpha>
          <node_risk>0.</node_risk>
          <tree_risk>0.</tree_risk>
          <tree_error>0.</tree_error></_>
        <_>
          <depth>3</depth>
          <sample_count>100</sample_count>
          <value>1.9500000000000001e-01</value>
          <Tn>0</Tn>
          <complexity>0</complexity>
          <alpha>0.</alpha>
          <node_risk>1.1947500000000000e+01</node_risk>
          <tree_risk>0.</tree_risk>
          <tree_error>0.</tree_error>
          <splits>
            <_><var>178</var>
              <quality>9.3281412124633789e+00</quality>
              <le>4.7450980544090271e-01</le></_></splits></_>
        <_>
          <depth>4</depth>
          <sample_count>11</sample_count>
          <value>8.6363636363636365e-01</value>
          <Tn>0</Tn>
          <complexity>0</complexity>
          <alpha>0.</alpha>
          <node_risk>5.4545454545454497e-01</node_risk>
          <tree_risk>0.</tree_risk>
          <tree_error>0.</tree_error>
          <splits>
            <_><var>115</var>
              <quality>8.7500000000000000e+00</quality>
              <le>4.2352941632270813e-01</le></_></splits></_>
        <_>
          <depth>5</depth>
          <sample_count>8</sample_count>
          <value>1.</value>
          <Tn>0</Tn>
          <complexity>0</complexity>
          <alpha>0.</alpha>
          <node_risk>0.</node_risk>
          <tree_risk>0.</tree_risk>
          <tree_error>0.</tree_error></_>
        <_>
          <depth>5</depth>
          <sample_count>3</sample_count>
          <value>5.0000000000000000e-01</value>
          <Tn>0</Tn>
          <complexity>0</complexity>
          <alpha>0.</alpha>
          <node_risk>0.</node_risk>
          <tree_risk>0.</tree_risk>
          <tree_error>0.</tree_error></_>
        <_>
          <depth>4</depth>
          <sample_count>89</sample_count>
          <value>1.1235955056179775e-01</value>
          <Tn>0</Tn>
          <complexity>0</complexity>
          <alpha>0.</alpha>
          <node_risk>5.8764044943820224e+00</node_risk>
          <tree_risk>0.</tree_risk>
          <tree_error>0.</tree_error>
          <splits>
            <_><var>53</var>
              <quality>3.5697674751281738e+00</quality>
              <le>1.2352941930294037e-01</le></_></splits></_>
        <_>
          <depth>5</depth>
          <sample_count>3</sample_count>
          <value>1.</value>
          <Tn>0</Tn>
          <complexity>0</complexity>
          <alpha>0.</alpha>
          <node_risk>0.</node_risk>
          <tree_risk>0.</tree_risk>
          <tree_error>0.</tree_error></_>
        <_>
          <depth>5</depth>
          <sample_count>86</sample_count>
          <value>8.1395348837209308e-02</value>
          <Tn>0</Tn>
          <complexity>0</complexity>
          <alpha>0.</alpha>
          <node_risk>3.4302325581395348e+00</node_risk>
          <tree_risk>0.</tree_risk>
          <tree_error>0.</tree_error>
          <splits>
            <_><var>109</var>
              <quality>1.9242423772811890e+00</quality>
              <le>1.5882353484630585e-01</le></_></splits></_>
        <_>
          <depth>6</depth>
          <sample_count>11</sample_count>
          <value>4.0909090909090912e-01</value>
          <Tn>0</Tn>
          <complexity>0</complexity>
          <alpha>0.</alpha>
          <node_risk>9.0909090909090895e-01</node_risk>
          <tree_risk>0.</tree_risk>
          <tree_error>0.</tree_error>
          <splits>
            <_><var>8</var>
              <quality>2.5312500000000000e+00</quality>
              <le>1.9607843458652496e-01</le></_></splits></_>
        <_>
          <depth>7</depth>
          <sample_count>8</sample_count>
          <value>5.6250000000000000e-01</value>
          <Tn>0</Tn>
          <complexity>0</complexity>
          <alpha>0.</alpha>
          <node_risk>2.1875000000000000e-01</node_risk>
          <tree_risk>0.</tree_risk>
          <tree_error>0.</tree_error></_>
        <_>
          <depth>7</depth>
          <sample_count>3</sample_count>
          <value>0.</value>
          <Tn>0</Tn>
          <complexity>0</complexity>
          <alpha>0.</alpha>
          <node_risk>0.</node_risk>
          <tree_risk>0.</tree_risk>
          <tree_error>0.</tree_error></_>
        <_>
          <depth>6</depth>
          <sample_count>75</sample_count>
          <value>3.3333333333333333e-02</value>
          <Tn>0</Tn>
          <complexity>0</complexity>
          <alpha>0.</alpha>
          <node_risk>1.1666666666666667e+00</node_risk>
          <tree_risk>0.</tree_risk>
          <tree_error>0.</tree_error>
          <splits>
            <_><var>22</var>
              <quality>5.3082191944122314e-01</quality>
              <le>9.2156864702701569e-02</le></_></splits></_>
        <_>
          <depth>7</depth>
          <sample_count>2</sample_count>
          <value>5.0000000000000000e-01</value>
          <Tn>0</Tn>
          <complexity>0</complexity>
          <alpha>0.</alpha>
          <node_risk>0.</node_risk>
          <tree_risk>0.</tree_risk>
          <tree_error>0.</tree_error></_>
        <_>
          <depth>7</depth>
          <sample_count>73</sample_count>
          <value>2.0547945205479451e-02</value>
          <Tn>0</Tn>
          <complexity>0</complexity>
          <alpha>0.</alpha>
          <node_risk>7.1917808219178081e-01</node_risk>
          <tree_risk>0.</tree_risk>
          <tree_error>0.</tree_error>
          <splits>
            <_><var>33</var>
              <quality>2.6388889551162720e-01</quality>
              <le>2.3137255012989044e-01</le></_></splits></_>
        <_>
          <depth>8</depth>
          <sample_count>72</sample_count>
          <value>1.3888888888888888e-02</value>
          <Tn>0</Tn>
          <complexity>0</complexity>
          <alpha>0.</alpha>
          <node_risk>4.8611111111111110e-01</node_risk>
          <tree_risk>0.</tree_risk>
          <tree_error>0.</tree_error>
          <splits>
            <_><var>87</var>
              <quality>8.3333335816860199e-02</quality>
              <le>4.4313725829124451e-01</le></_></splits></_>
        <_>
          <depth>9</depth>
          <sample_count>12</sample_count>
          <value>8.3333333333333329e-02</value>
          <Tn>0</Tn>
          <complexity>0</complexity>
          <alpha>0.</alpha>
          <node_risk>4.1666666666666669e-01</node_risk>
          <tree_risk>0.</tree_risk>
          <tree_error>0.</tree_error>
          <splits>
            <_><var>71</var>
              <quality>5.0000000000000000e-01</quality>
              <le>1.6274510324001312e-01</le></_></splits></_>
        <_>
          <depth>10</depth>
          <sample_count>10</sample_count>
          <value>0.</value>
          <Tn>0</Tn>
          <complexity>0</complexity>
          <alpha>0.</alpha>
          <node_risk>0.</node_risk>
          <tree_risk>0.</tree_risk>
          <tree_error>0.</tree_error></_>
        <_>
          <depth>10</depth>
          <sample_count>2</sample_count>
          <value>5.0000000000000000e-01</value>
          <Tn>0</Tn>
          <complexity>0</complexity>
          <alpha>0.</alpha>
          <node_risk>0.</node_risk>
          <tree_risk>0.</tree_risk>
          <tree_error>0.</tree_error></_>
        <_>
          <depth>9</depth>
          <sample_count>60</sample_count>
          <value>0.</value>
          <Tn>0</Tn>
          <complexity>0</complexity>
          <alpha>0.</alpha>
          <node_risk>0.</node_risk>
          <tree_risk>0.</tree_risk>
          <tree_error>0.</tree_error></_>
        <_>
          <depth>8</depth>
          <sample_count>1</sample_count>
          <value>5.0000000000000000e-01</value>
          <Tn>0</Tn>
          <complexity>0</complexity>
          <alpha>0.</alpha>
          <node_risk>0.</node_risk>
          <tree_risk>0.</tree_risk>
          <tree_error>0.</tree_error></_>
        <_>
          <depth>1</depth>
          <sample_count>46983</sample_count>
          <value>3.1394334120852223e-03</value>
          <Tn>0</Tn>
          <complexity>0</complexity>
          <alpha>0.</alpha>
          <node_risk>1.3628693357171744e+02</node_risk>
          <tree_risk>0.</tree_risk>
          <tree_error>0.</tree_error>
          <splits>
            <_><var>217</var>
              <quality>3.8114013671875000e+01</quality>
              <le>4.7254902124404907e-01</le></_></splits></_>
        <_>
          <depth>2</depth>
          <sample_count>179</sample_count>
          <value>4.6089385474860334e-01</value>
          <Tn>0</Tn>
          <complexity>0</complexity>
          <alpha>0.</alpha>
          <node_risk>4.0226256983240226e+01</node_risk>
          <tree_risk>0.</tree_risk>
          <tree_error>0.</tree_error>
          <splits>
            <_><var>114</var>
              <quality>4.9553424835205078e+01</quality>
              <le>6.3921570777893066e-01</le></_></splits></_>
        <_>
          <depth>3</depth>
          <sample_count>128</sample_count>
          <value>6.2109375000000000e-01</value>
          <Tn>0</Tn>
          <complexity>0</complexity>
          <alpha>0.</alpha>
          <node_risk>2.5873046875000000e+01</node_risk>
          <tree_risk>0.</tree_risk>
          <tree_error>0.</tree_error>
          <splits>
            <_><var>211</var>
              <quality>6.8698371887207031e+01</quality>
              <le>4.6862745285034180e-01</le></_></splits></_>
        <_>
          <depth>4</depth>
          <sample_count>92</sample_count>
          <value>8.6413043478260865e-01</value>
          <Tn>0</Tn>
          <complexity>0</complexity>
          <alpha>0.</alpha>
          <node_risk>6.5516304347826093e+00</node_risk>
          <tree_risk>0.</tree_risk>
          <tree_error>0.</tree_error>
          <splits>
            <_><var>199</var>
              <quality>7.1821022033691406e+01</quality>
              <le>4.7254902124404907e-01</le></_></splits></_>
        <_>
          <depth>5</depth>
          <sample_count>88</sample_count>
          <value>9.0340909090909094e-01</value>
          <Tn>0</Tn>
          <complexity>0</complexity>
          <alpha>0.</alpha>
          <node_risk>3.4289772727272663e+00</node_risk>
          <tree_risk>0.</tree_risk>
          <tree_error>0.</tree_error>
          <splits>
            <_><var>165</var>
              <quality>7.3866882324218750e+01</quality>
              <le>2.5490196421742439e-02</le></_></splits></_>
        <_>
          <depth>6</depth>
          <sample_count>11</sample_count>
          <value>5.0000000000000000e-01</value>
          <Tn>0</Tn>
          <complexity>0</complexity>
          <alpha>0.</alpha>
          <node_risk>0.</node_risk>
          <tree_risk>0.</tree_risk>
          <tree_error>0.</tree_error>
          <splits>
            <_><var>0</var>
              <quality>2.7500000000000000e+00</quality>
              <le>2.7450982481241226e-02</le></_></splits></_>
        <_>
          <depth>7</depth>
          <sample_count>1</sample_count>
          <value>5.0000000000000000e-01</value>
          <Tn>0</Tn>
          <complexity>0</complexity>
          <alpha>0.</alpha>
          <node_risk>0.</node_risk>
          <tree_risk>0.</tree_risk>
          <tree_error>0.</tree_error></_>
        <_>
          <depth>7</depth>
          <sample_count>10</sample_count>
          <value>5.0000000000000000e-01</value>
          <Tn>0</Tn>
          <complexity>0</complexity>
          <alpha>0.</alpha>
          <node_risk>0.</node_risk>
          <tree_risk>0.</tree_risk>
          <tree_error>0.</tree_error></_>
        <_>
          <depth>6</depth>
          <sample_count>77</sample_count>
          <value>9.6103896103896103e-01</value>
          <Tn>0</Tn>
          <complexity>0</complexity>
          <alpha>0.</alpha>
          <node_risk>1.3831168831168839e+00</node_risk>
          <tree_risk>0.</tree_risk>
          <tree_error>0.</tree_error>
          <splits>
            <_><var>16</var>
              <quality>7.1780403137207031e+01</quality>
              <le>3.0980393290519714e-01</le></_></splits></_>
        <_>
          <depth>7</depth>
          <sample_count>74</sample_count>
          <value>9.7972972972972971e-01</value>
          <Tn>0</Tn>
          <complexity>0</complexity>
          <alpha>0.</alpha>
          <node_risk>7.1959459459459651e-01</node_risk>
          <tree_risk>0.</tree_risk>
          <tree_error>0.</tree_error>
          <splits>
            <_><var>21</var>
              <quality>7.1503471374511719e+01</quality>
              <le>2.2156862914562225e-01</le></_></splits></_>
        <_>
          <depth>8</depth>
          <sample_count>72</sample_count>
          <value>9.9305555555555558e-01</value>
          <Tn>0</Tn>
          <complexity>0</complexity>
          <alpha>0.</alpha>
          <node_risk>2.4652777777777146e-01</node_risk>
          <tree_risk>0.</tree_risk>
          <tree_error>0.</tree_error>
          <splits>
            <_><var>101</var>
              <quality>7.1083335876464844e+01</quality>
              <le>4.5098040252923965e-02</le></_></splits></_>
        <_>
          <depth>9</depth>
          <sample_count>3</sample_count>
          <value>8.3333333333333337e-01</value>
          <Tn>0</Tn>
          <complexity>0</complexity>
          <alpha>0.</alpha>
          <node_risk>1.6666666666666652e-01</node_risk>
          <tree_risk>0.</tree_risk>
          <tree_error>0.</tree_error></_>
        <_>
          <depth>9</depth>
          <sample_count>69</sample_count>
          <value>1.</value>
          <Tn>0</Tn>
          <complexity>0</complexity>
          <alpha>0.</alpha>
          <node_risk>0.</node_risk>
          <tree_risk>0.</tree_risk>
          <tree_error>0.</tree_error>
          <splits>
            <_><var>30</var>
              <quality>69.</quality>
              <le>2.9411766678094864e-02</le></_></splits></_>
        <_>
          <depth>10</depth>
          <sample_count>3</sample_count>
          <value>1.</value>
          <Tn>0</Tn>
          <complexity>0</complexity>
          <alpha>0.</alpha>
          <node_risk>0.</node_risk>
          <tree_risk>0.</tree_risk>
          <tree_error>0.</tree_error></_>
        <_>
          <depth>10</depth>
          <sample_count>66</sample_count>
          <value>1.</value>
          <Tn>0</Tn>
          <complexity>0</complexity>
          <alpha>0.</alpha>
          <node_risk>0.</node_risk>
          <tree_risk>0.</tree_risk>
          <tree_error>0.</tree_error></_>
        <_>
          <depth>8</depth>
          <sample_count>2</sample_count>
          <value>5.0000000000000000e-01</value>
          <Tn>0</Tn>
          <complexity>0</complexity>
          <alpha>0.</alpha>
          <node_risk>0.</node_risk>
          <tree_risk>0.</tree_risk>
          <tree_error>0.</tree_error></_>
        <_>
          <depth>7</depth>
          <sample_count>3</sample_count>
          <value>5.0000000000000000e-01</value>
          <Tn>0</Tn>
          <complexity>0</complexity>
          <alpha>0.</alpha>
          <node_risk>0.</node_risk>
          <tree_risk>0.</tree_risk>
          <tree_error>0.</tree_error></_>
        <_>
          <depth>5</depth>
          <sample_count>4</sample_count>
          <value>0.</value>
          <Tn>0</Tn>
          <complexity>0</complexity>
          <alpha>0.</alpha>
          <node_risk>0.</node_risk>
          <tree_risk>0.</tree_risk>
          <tree_error>0.</tree_error></_>
        <_>
          <depth>4</depth>
          <sample_count>36</sample_count>
          <value>0.</value>
          <Tn>0</Tn>
          <complexity>0</complexity>
          <alpha>0.</alpha>
          <node_risk>0.</node_risk>
          <tree_risk>0.</tree_risk>
          <tree_error>0.</tree_error></_>
        <_>
          <depth>3</depth>
          <sample_count>51</sample_count>
          <value>5.8823529411764705e-02</value>
          <Tn>0</Tn>
          <complexity>0</complexity>
          <alpha>0.</alpha>
          <node_risk>2.8235294117647061e+00</node_risk>
          <tree_risk>0.</tree_risk>
          <tree_error>0.</tree_error>
          <splits>
            <_><var>20</var>
              <quality>2.0204081535339355e+00</quality>
              <le>9.2156864702701569e-02</le></_></splits></_>
        <_>
          <depth>4</depth>
          <sample_count>2</sample_count>
          <value>1.</value>
          <Tn>0</Tn>
          <complexity>0</complexity>
          <alpha>0.</alpha>
          <node_risk>0.</node_risk>
          <tree_risk>0.</tree_risk>
          <tree_error>0.</tree_error></_>
        <_>
          <depth>4</depth>
          <sample_count>49</sample_count>
          <value>2.0408163265306121e-02</value>
          <Tn>0</Tn>
          <complexity>0</complexity>
          <alpha>0.</alpha>
          <node_risk>9.7959183673469385e-01</node_risk>
          <tree_risk>0.</tree_risk>
          <tree_error>0.</tree_error>
          <splits>
            <_><var>74</var>
              <quality>1.</quality>
              <le>9.6078433096408844e-02</le></_></splits></_>
        <_>
          <depth>5</depth>
          <sample_count>1</sample_count>
          <value>1.</value>
          <Tn>0</Tn>
          <complexity>0</complexity>
          <alpha>0.</alpha>
          <node_risk>0.</node_risk>
          <tree_risk>0.</tree_risk>
          <tree_error>0.</tree_error></_>
        <_>
          <depth>5</depth>
          <sample_count>48</sample_count>
          <value>0.</value>
          <Tn>0</Tn>
          <complexity>0</complexity>
          <alpha>0.</alpha>
          <node_risk>0.</node_risk>
          <tree_risk>0.</tree_risk>
          <tree_error>0.</tree_error></_>
        <_>
          <depth>2</depth>
          <sample_count>46804</sample_count>
          <value>1.3887701905820015e-03</value>
          <Tn>0</Tn>
          <complexity>0</complexity>
          <alpha>0.</alpha>
          <node_risk>5.8409729937612170e+01</node_risk>
          <tree_risk>0.</tree_risk>
          <tree_error>0.</tree_error>
          <splits>
            <_><var>157</var>
              <quality>2.2364160537719727e+01</quality>
              <le>4.7254902124404907e-01</le></_></splits></_>
        <_>
          <depth>3</depth>
          <sample_count>128</sample_count>
          <value>4.1796875000000000e-01</value>
          <Tn>0</Tn>
          <complexity>0</complexity>
          <alpha>0.</alpha>
          <node_risk>2.5888671875000000e+01</node_risk>
          <tree_risk>0.</tree_risk>
          <tree_error>0.</tree_error>
          <splits>
            <_><var>172</var>
              <quality>3.1855381011962891e+01</quality>
              <le>5.0000000000000000e-01</le></_></splits></_>
        <_>
          <depth>4</depth>
          <sample_count>82</sample_count>
          <value>6.2195121951219512e-01</value>
          <Tn>0</Tn>
          <complexity>0</complexity>
          <alpha>0.</alpha>
          <node_risk>1.5280487804878049e+01</node_risk>
          <tree_risk>0.</tree_risk>
          <tree_error>0.</tree_error>
          <splits>
            <_><var>180</var>
              <quality>3.6452976226806641e+01</quality>
              <le>3.3529412746429443e-01</le></_></splits></_>
        <_>
          <depth>5</depth>
          <sample_count>70</sample_count>
          <value>7.2142857142857142e-01</value>
          <Tn>0</Tn>
          <complexity>0</complexity>
          <alpha>0.</alpha>
          <node_risk>1.0317857142857143e+01</node_risk>
          <tree_risk>0.</tree_risk>
          <tree_error>0.</tree_error>
          <splits>
            <_><var>193</var>
              <quality>4.0480159759521484e+01</quality>
              <le>4.9803924560546875e-01</le></_></splits></_>
        <_>
          <depth>6</depth>
          <sample_count>63</sample_count>
          <value>8.0158730158730163e-01</value>
          <Tn>0</Tn>
          <complexity>0</complexity>
          <alpha>0.</alpha>
          <node_risk>6.2698412698412653e+00</node_risk>
          <tree_risk>0.</tree_risk>
          <tree_error>0.</tree_error>
          <splits>
            <_><var>166</var>
              <quality>4.1692306518554688e+01</quality>
              <le>5.0000000000000000e-01</le></_></splits></_>
        <_>
          <depth>7</depth>
          <sample_count>52</sample_count>
          <value>8.6538461538461542e-01</value>
          <Tn>0</Tn>
          <complexity>0</complexity>
          <alpha>0.</alpha>
          <node_risk>3.0576923076923066e+00</node_risk>
          <tree_risk>0.</tree_risk>
          <tree_error>0.</tree_error>
          <splits>
            <_><var>214</var>
              <quality>3.9993347167968750e+01</quality>
              <le>4.6862745285034180e-01</le></_></splits></_>
        <_>
          <depth>8</depth>
          <sample_count>11</sample_count>
          <value>5.9090909090909094e-01</value>
          <Tn>0</Tn>
          <complexity>0</complexity>
          <alpha>0.</alpha>
          <node_risk>4.0909090909090873e-01</node_risk>
          <tree_risk>0.</tree_risk>
          <tree_error>0.</tree_error>
          <splits>
            <_><var>144</var>
              <quality>4.2500000000000000e+00</quality>
              <le>3.5490196943283081e-01</le></_></splits></_>
        <_>
          <depth>9</depth>
          <sample_count>2</sample_count>
          <value>1.</value>
          <Tn>0</Tn>
          <complexity>0</complexity>
          <alpha>0.</alpha>
          <node_risk>0.</node_risk>
          <tree_risk>0.</tree_risk>
          <tree_error>0.</tree_error></_>
        <_>
          <depth>9</depth>
          <sample_count>9</sample_count>
          <value>5.0000000000000000e-01</value>
          <Tn>0</Tn>
          <complexity>0</complexity>
          <alpha>0.</alpha>
          <node_risk>0.</node_risk>
          <tree_risk>0.</tree_risk>
          <tree_error>0.</tree_error></_>
        <_>
          <depth>8</depth>
          <sample_count>41</sample_count>
          <value>9.3902439024390238e-01</value>
          <Tn>0</Tn>
          <complexity>0</complexity>
          <alpha>0.</alpha>
          <node_risk>1.5975609756097597e+00</node_risk>
          <tree_risk>0.</tree_risk>
          <tree_error>0.</tree_error>
          <splits>
            <_><var>156</var>
              <quality>3.6557693481445312e+01</quality>
              <le>3.4705883264541626e-01</le></_></splits></_>
        <_>
          <depth>9</depth>
          <sample_count>39</sample_count>
          <value>9.6153846153846156e-01</value>
          <Tn>0</Tn>
          <complexity>0</complexity>
          <alpha>0.</alpha>
          <node_risk>1.1923076923076934e+00</node_risk>
          <tree_risk>0.</tree_risk>
          <tree_error>0.</tree_error>
          <splits>
            <_><var>113</var>
              <quality>3.7125000000000000e+01</quality>
              <le>3.2156863808631897e-01</le></_></splits></_>
        <_>
          <depth>10</depth>
          <sample_count>37</sample_count>
          <value>1.</value>
          <Tn>0</Tn>
          <complexity>0</complexity>
          <alpha>0.</alpha>
          <node_risk>0.</node_risk>
          <tree_risk>0.</tree_risk>
          <tree_error>0.</tree_error></_>
        <_>
          <depth>10</depth>
          <sample_count>2</sample_count>
          <value>2.5000000000000000e-01</value>
          <Tn>0</Tn>
          <complexity>0</complexity>
          <alpha>0.</alpha>
          <node_risk>1.2500000000000000e-01</node_risk>
          <tree_risk>0.</tree_risk>
          <tree_error>0.</tree_error></_>
        <_>
          <depth>9</depth>
          <sample_count>2</sample_count>
          <value>5.0000000000000000e-01</value>
          <Tn>0</Tn>
          <complexity>0</complexity>
          <alpha>0.</alpha>
          <node_risk>0.</node_risk>
          <tree_risk>0.</tree_risk>
          <tree_error>0.</tree_error></_>
        <_>
          <depth>7</depth>
          <sample_count>11</sample_count>
          <value>5.0000000000000000e-01</value>
          <Tn>0</Tn>
          <complexity>0</complexity>
          <alpha>0.</alpha>
          <node_risk>2.</node_risk>
          <tree_risk>0.</tree_risk>
          <tree_error>0.</tree_error>
          <splits>
            <_><var>108</var>
              <quality>4.3214287757873535e+00</quality>
              <le>4.1764706373214722e-01</le></_></splits></_>
        <_>
          <depth>8</depth>
          <sample_count>4</sample_count>
          <value>1.</value>
          <Tn>0</Tn>
          <complexity>0</complexity>
          <alpha>0.</alpha>
          <node_risk>0.</node_risk>
          <tree_risk>0.</tree_risk>
          <tree_error>0.</tree_error></_>
        <_>
          <depth>8</depth>
          <sample_count>7</sample_count>
          <value>2.1428571428571427e-01</value>
          <Tn>0</Tn>
          <complexity>0</complexity>
          <alpha>0.</alpha>
          <node_risk>4.2857142857142860e-01</node_risk>
          <tree_risk>0.</tree_risk>
          <tree_error>0.</tree_error></_>
        <_>
          <depth>6</depth>
          <sample_count>7</sample_count>
          <value>0.</value>
          <Tn>0</Tn>
          <complexity>0</complexity>
          <alpha>0.</alpha>
          <node_risk>0.</node_risk>
          <tree_risk>0.</tree_risk>
          <tree_error>0.</tree_error></_>
        <_>
          <depth>5</depth>
          <sample_count>12</sample_count>
          <value>4.1666666666666664e-02</value>
          <Tn>0</Tn>
          <complexity>0</complexity>
          <alpha>0.</alpha>
          <node_risk>2.2916666666666666e-01</node_risk>
          <tree_risk>0.</tree_risk>
          <tree_error>0.</tree_error>
          <splits>
            <_><var>47</var>
              <quality>2.5000000000000000e-01</quality>
              <le>1.9607844296842813e-03</le></_></splits></_>
        <_>
          <depth>6</depth>
          <sample_count>1</sample_count>
          <value>5.0000000000000000e-01</value>
          <Tn>0</Tn>
          <complexity>0</complexity>
          <alpha>0.</alpha>
          <node_risk>0.</node_risk>
          <tree_risk>0.</tree_risk>
          <tree_error>0.</tree_error></_>
        <_>
          <depth>6</depth>
          <sample_count>11</sample_count>
          <value>0.</value>
          <Tn>0</Tn>
          <complexity>0</complexity>
          <alpha>0.</alpha>
          <node_risk>0.</node_risk>
          <tree_risk>0.</tree_risk>
          <tree_error>0.</tree_error></_>
        <_>
          <depth>4</depth>
          <sample_count>46</sample_count>
          <value>5.4347826086956520e-02</value>
          <Tn>0</Tn>
          <complexity>0</complexity>
          <alpha>0.</alpha>
          <node_risk>1.1141304347826086e+00</node_risk>
          <tree_risk>0.</tree_risk>
          <tree_error>0.</tree_error>
          <splits>
            <_><var>125</var>
              <quality>7.8125000000000000e-01</quality>
              <le>1.4705882966518402e-01</le></_></splits></_>
        <_>
          <depth>5</depth>
          <sample_count>8</sample_count>
          <value>3.1250000000000000e-01</value>
          <Tn>0</Tn>
          <complexity>0</complexity>
          <alpha>0.</alpha>
          <node_risk>4.6875000000000000e-01</node_risk>
          <tree_risk>0.</tree_risk>
          <tree_error>0.</tree_error></_>
        <_>
          <depth>5</depth>
          <sample_count>38</sample_count>
          <value>0.</value>
          <Tn>0</Tn>
          <complexity>0</complexity>
          <alpha>0.</alpha>
          <node_risk>0.</node_risk>
          <tree_risk>0.</tree_risk>
          <tree_error>0.</tree_error></_>
        <_>
          <depth>3</depth>
          <sample_count>46676</sample_count>
          <value>2.4637929556945755e-04</value>
          <Tn>0</Tn>
          <complexity>0</complexity>
          <alpha>0.</alpha>
          <node_risk>1.0247166638100952e+01</node_risk>
          <tree_risk>0.</tree_risk>
          <tree_error>0.</tree_error>
          <splits>
            <_><var>151</var>
              <quality>6.2976188659667969e+00</quality>
              <le>4.8039215803146362e-01</le></_></splits></_>
        <_>
          <depth>4</depth>
          <sample_count>21</sample_count>
          <value>5.4761904761904767e-01</value>
          <Tn>0</Tn>
          <complexity>0</complexity>
          <alpha>0.</alpha>
          <node_risk>3.9523809523809517e+00</node_risk>
          <tree_risk>0.</tree_risk>
          <tree_error>0.</tree_error>
          <splits>
            <_><var>103</var>
              <quality>9.5208330154418945e+00</quality>
              <le>6.3725495338439941e-01</le></_></splits></_>
        <_>
          <depth>5</depth>
          <sample_count>12</sample_count>
          <value>2.0833333333333334e-01</value>
          <Tn>0</Tn>
          <complexity>0</complexity>
          <alpha>0.</alpha>
          <node_risk>7.2916666666666663e-01</node_risk>
          <tree_risk>0.</tree_risk>
          <tree_error>0.</tree_error>
          <splits>
            <_><var>57</var>
              <quality>1.2500000000000000e+00</quality>
              <le>2.3529412224888802e-02</le></_></splits></_>
        <_>
          <depth>6</depth>
          <sample_count>5</sample_count>
          <value>5.0000000000000000e-01</value>
          <Tn>0</Tn>
          <complexity>0</complexity>
          <alpha>0.</alpha>
          <node_risk>0.</node_risk>
          <tree_risk>0.</tree_risk>
          <tree_error>0.</tree_error></_>
        <_>
          <depth>6</depth>
          <sample_count>7</sample_count>
          <value>0.</value>
          <Tn>0</Tn>
          <complexity>0</complexity>
          <alpha>0.</alpha>
          <node_risk>0.</node_risk>
          <tree_risk>0.</tree_risk>
          <tree_error>0.</tree_error></_>
        <_>
          <depth>5</depth>
          <sample_count>9</sample_count>
          <value>1.</value>
          <Tn>0</Tn>
          <complexity>0</complexity>
          <alpha>0.</alpha>
          <node_risk>0.</node_risk>
          <tree_risk>0.</tree_risk>
          <tree_error>0.</tree_error></_>
        <_>
          <depth>4</depth>
          <sample_count>46655</sample_count>
          <value>0.</value>
          <Tn>0</Tn>
          <complexity>0</complexity>
          <alpha>0.</alpha>
          <node_risk>0.</node_risk>
          <tree_risk>0.</tree_risk>
          <tree_error>0.</tree_error></_></nodes></_></trees></my_random_trees>
</opencv_storage>
