<?xml version="1.0"?>
<opencv_storage>
<globfeat type_id="opencv-matrix">
  <rows>1</rows>
  <cols>64</cols>
  <dt>f</dt>
  <data>
    1.89101486e+01 9.95129776e+00 0. 0. 2.79065514e+01 0. 0. 0.
    2.44463959e+01 0. 0. 0. 2.29067612e+01 0. 0. 0. 0. 0. 0. 0. 0. 0. 0.
    0. 0. 0. 0. 0. 0. 0. 0. 0. 0. 3.59963393e+00 0. 0. 1.18289009e+02
    2.82713413e+00 0. 0. 1.85399914e+01 0. 0. 0. 4.43650866e+00 0. 0. 0.
    0. 0. 0. 0. 3.18656111e+00 0. 0. 0. 0. 0. 0. 0. 0. 0. 0. 0.</data></globfeat>
</opencv_storage>
