<?xml version="1.0"?>
<opencv_storage>
<globfeat type_id="opencv-matrix">
  <rows>1</rows>
  <cols>64</cols>
  <dt>f</dt>
  <data>
    7.46728611e+00 7.79124689e+00 3.60675859e+00 0. 2.40486584e+01 0. 0.
    0. 2.28770008e+01 0. 0. 0. 1.74884605e+01 0. 0. 0. 0. 0. 0. 0. 0. 0.
    0. 0. 0. 0. 0. 0. 9.69181442e+00 0. 0. 0. 0. 3.18021083e+00 0. 0.
    9.90184860e+01 3.63591499e+01 0. 0. 2.04041042e+01 0. 0. 0.
    3.06682467e+00 0. 0. 0. 0. 0. 0. 0. 0. 0. 0. 0. 0. 0. 0. 0. 0. 0. 0.
    0.</data></globfeat>
</opencv_storage>
